Workbook

Sheet Read me
A1: RevIA – prospect list
A3: What this is: 108 organisations that match RevIA's profile (secure code review, French/English, cheap, self-hostable, CI gate), grouped by segment.
A4: What it is NOT: a list of guaranteed buyers. Nobody can honestly promise that any organisation will buy. Cold B2B outreach typically converts at a few percent;
A5: a well-targeted pilot offer to warm contacts (your school, alumni, ex-colleagues) converts much better. Start with Tier A.
A7: Fit score (0–100) = our estimate of how well RevIA matches the organisation's needs, budget and buying process today. It is not a purchase probability.
A8: Tier is computed from the score: A ≥ 75, B 60–74, C < 60 (formula, change thresholds in cells B12:B13).
A9: No personal contact details are included: find the named role on the organisation's website or LinkedIn page and reach out professionally.
A10: Yellow columns (Status, Next step, Contacted on, Notes) are for you to fill in. Example: Status = 'Contacted', Next step = 'Demo call'.
A12: Tier A threshold | B12: 75
A13: Tier B threshold | B13: 60
A15: Sources used for verification: clutch.co/tn/developers, themanifest.com/tn (Java), goodfirms.co (Morocco), blog.holbertonschool.com, infomediaire.net (GOMYCODE), dealroom (Simplon/Wild Code School), talan.com (Shore), Wikipedia (42 school), composio.dev (competitor pricing 2026).
A16: Competitor price context (2026, per dev/month): CodeRabbit $24–30+, Greptile $30, Graphite $20–40, GitHub Copilot Business $19. RevIA Pro at €9 is the low-cost, self-hostable option.

Sheet Summary
A1: Prospects by segment and tier
A3: Segment | B3: Total | C3: Tier A | D3: Tier B | E3: Tier C | F3: Avg fit
A4: Education (schools & bootcamps) | B4: =COUNTIF(Prospects!$C$2:$C$109,A4) -> 30 | C4: =COUNTIFS(Prospects!$C$2:$C$109,A4,Prospects!$G$2:$G$109,"A") -> 5 | D4: =COUNTIFS(Prospects!$C$2:$C$109,A4,Prospects!$G$2:$G$109,"B") -> 21 | E4: =COUNTIFS(Prospects!$C$2:$C$109,A4,Prospects!$G$2:$G$109,"C") -> 4 | F4: =IFERROR(AVERAGEIF(Prospects!$C$2:$C$109,A4,Prospects!$F$2:$F$109),0) -> 68.133333
A5: Software firms – Tunisia | B5: =COUNTIF(Prospects!$C$2:$C$109,A5) -> 35 | C5: =COUNTIFS(Prospects!$C$2:$C$109,A5,Prospects!$G$2:$G$109,"A") -> 0 | D5: =COUNTIFS(Prospects!$C$2:$C$109,A5,Prospects!$G$2:$G$109,"B") -> 28 | E5: =COUNTIFS(Prospects!$C$2:$C$109,A5,Prospects!$G$2:$G$109,"C") -> 7 | F5: =IFERROR(AVERAGEIF(Prospects!$C$2:$C$109,A5,Prospects!$F$2:$F$109),0) -> 64.457143
A6: Software firms – Morocco | B6: =COUNTIF(Prospects!$C$2:$C$109,A6) -> 12 | C6: =COUNTIFS(Prospects!$C$2:$C$109,A6,Prospects!$G$2:$G$109,"A") -> 0 | D6: =COUNTIFS(Prospects!$C$2:$C$109,A6,Prospects!$G$2:$G$109,"B") -> 8 | E6: =COUNTIFS(Prospects!$C$2:$C$109,A6,Prospects!$G$2:$G$109,"C") -> 4 | F6: =IFERROR(AVERAGEIF(Prospects!$C$2:$C$109,A6,Prospects!$F$2:$F$109),0) -> 62
A7: Java/Spring consultancies – France | B7: =COUNTIF(Prospects!$C$2:$C$109,A7) -> 21 | C7: =COUNTIFS(Prospects!$C$2:$C$109,A7,Prospects!$G$2:$G$109,"A") -> 0 | D7: =COUNTIFS(Prospects!$C$2:$C$109,A7,Prospects!$G$2:$G$109,"B") -> 8 | E7: =COUNTIFS(Prospects!$C$2:$C$109,A7,Prospects!$G$2:$G$109,"C") -> 13 | F7: =IFERROR(AVERAGEIF(Prospects!$C$2:$C$109,A7,Prospects!$F$2:$F$109),0) -> 57.333333
A8: Software firms – West/Sub-Saharan Africa | B8: =COUNTIF(Prospects!$C$2:$C$109,A8) -> 2 | C8: =COUNTIFS(Prospects!$C$2:$C$109,A8,Prospects!$G$2:$G$109,"A") -> 0 | D8: =COUNTIFS(Prospects!$C$2:$C$109,A8,Prospects!$G$2:$G$109,"B") -> 1 | E8: =COUNTIFS(Prospects!$C$2:$C$109,A8,Prospects!$G$2:$G$109,"C") -> 1 | F8: =IFERROR(AVERAGEIF(Prospects!$C$2:$C$109,A8,Prospects!$F$2:$F$109),0) -> 57
A9: Public sector & regulated | B9: =COUNTIF(Prospects!$C$2:$C$109,A9) -> 6 | C9: =COUNTIFS(Prospects!$C$2:$C$109,A9,Prospects!$G$2:$G$109,"A") -> 0 | D9: =COUNTIFS(Prospects!$C$2:$C$109,A9,Prospects!$G$2:$G$109,"B") -> 0 | E9: =COUNTIFS(Prospects!$C$2:$C$109,A9,Prospects!$G$2:$G$109,"C") -> 6 | F9: =IFERROR(AVERAGEIF(Prospects!$C$2:$C$109,A9,Prospects!$F$2:$F$109),0) -> 47
A10: Channel partners | B10: =COUNTIF(Prospects!$C$2:$C$109,A10) -> 2 | C10: =COUNTIFS(Prospects!$C$2:$C$109,A10,Prospects!$G$2:$G$109,"A") -> 0 | D10: =COUNTIFS(Prospects!$C$2:$C$109,A10,Prospects!$G$2:$G$109,"B") -> 1 | E10: =COUNTIFS(Prospects!$C$2:$C$109,A10,Prospects!$G$2:$G$109,"C") -> 1 | F10: =IFERROR(AVERAGEIF(Prospects!$C$2:$C$109,A10,Prospects!$F$2:$F$109),0) -> 57.5
A11: Total | B11: =SUM(B4:B10) -> 108 | C11: =SUM(C4:C10) -> 5 | D11: =SUM(D4:D10) -> 67 | E11: =SUM(E4:E10) -> 36 | F11: =AVERAGE(Prospects!$F$2:$F$109) -> 62.583333
A13: Pipeline (from Status column)
A14: To contact | B14: =COUNTIF(Prospects!$L$2:$L$109,A14) -> 1
A15: Contacted | B15: =COUNTIF(Prospects!$L$2:$L$109,A15) -> 0
A16: Replied | B16: =COUNTIF(Prospects!$L$2:$L$109,A16) -> 0
A17: Demo booked | B17: =COUNTIF(Prospects!$L$2:$L$109,A17) -> 0
A18: Pilot | B18: =COUNTIF(Prospects!$L$2:$L$109,A18) -> 0
A19: Customer | B19: =COUNTIF(Prospects!$L$2:$L$109,A19) -> 0
A20: Lost | B20: =COUNTIF(Prospects!$L$2:$L$109,A20) -> 0

Sheet Prospects
A1: # | B1: Organisation | C1: Segment | D1: Location | E1: Size (approx.) | F1: Fit score (0–100) | G1: Tier | H1: Why RevIA fits | I1: Who to contact (role) | J1: Suggested offer | K1: Notes / source | L1: Status | M1: Next step | N1: Contacted on | O1: Your notes
A2: 1 | B2: ESPRIT (École Supérieure Privée d'Ingénierie et de Technologies) | C2: Education (schools & bootcamps) | D2: Tunis, Tunisia | E2: Large private engineering school | F2: 90 | G2: =IF(F2>='Read me'!$B$12,"A",IF(F2>='Read me'!$B$13,"B","C")) -> A | H2: Teaches secure coding & code review: RevIA gives every student an instant senior-style review (OWASP, fixes explained) at a per-seat price far below US tools; French + English; can self-host on campus. | I2: Head of studies / pedagogy lead, IT dept head | J2: Campus licence (self-hosted, unlimited students) or €2–3/student/semester | K2: Your own school: easiest first pilot and reference customer (course 'IA for Software Engineering'). | L2: To contact | M2: Pilot offer email
A3: 2 | B3: GOMYCODE | C3: Education (schools & bootcamps) | D3: Tunis + Morocco, Senegal, others | E3: Large bootcamp network | F3: 84 | G3: =IF(F3>='Read me'!$B$12,"A",IF(F3>='Read me'!$B$13,"B","C")) -> A | H3: Teaches secure coding & code review: RevIA gives every student an instant senior-style review (OWASP, fixes explained) at a per-seat price far below US tools; French + English; can self-host on campus. | I3: Head of studies / pedagogy lead, IT dept head | J3: Campus licence (self-hosted, unlimited students) or €2–3/student/semester | K3: Expanding with AI in curricula (infomediaire.net 2025).
A4: 3 | B4: Holberton School Tunis | C4: Education (schools & bootcamps) | D4: Tunis, Tunisia | E4: Bootcamp campus | F4: 82 | G4: =IF(F4>='Read me'!$B$12,"A",IF(F4>='Read me'!$B$13,"B","C")) -> A | H4: Teaches secure coding & code review: RevIA gives every student an instant senior-style review (OWASP, fixes explained) at a per-seat price far below US tools; French + English; can self-host on campus. | I4: Head of studies / pedagogy lead, IT dept head | J4: Campus licence (self-hosted, unlimited students) or €2–3/student/semester | K4: Peer-review based pedagogy; source: blog.holbertonschool.com
A5: 4 | B5: 1337 (42 Network) | C5: Education (schools & bootcamps) | D5: Khouribga / Benguerir / Tétouan, Morocco | E5: 42 Network campuses | F5: 76 | G5: =IF(F5>='Read me'!$B$12,"A",IF(F5>='Read me'!$B$13,"B","C")) -> A | H5: Teaches secure coding & code review: RevIA gives every student an instant senior-style review (OWASP, fixes explained) at a per-seat price far below US tools; French + English; can self-host on campus. | I5: Head of studies / pedagogy lead, IT dept head | J5: Campus licence (self-hosted, unlimited students) or €2–3/student/semester | K5: Peer-to-peer code evaluation model; source: Wikipedia 42 (school).
A6: 5 | B6: Simplon (incl. Wild Code School) | C6: Education (schools & bootcamps) | D6: Montreuil, France + Africa | E6: Social-impact school network | F6: 76 | G6: =IF(F6>='Read me'!$B$12,"A",IF(F6>='Read me'!$B$13,"B","C")) -> A | H6: Teaches secure coding & code review: RevIA gives every student an instant senior-style review (OWASP, fixes explained) at a per-seat price far below US tools; French + English; can self-host on campus. | I6: Head of studies / pedagogy lead, IT dept head | J6: Campus licence (self-hosted, unlimited students) or €2–3/student/semester | K6: Simplon acquired Wild Code School (dealroom).
A7: 6 | B7: Hydatis | C7: Software firms – Tunisia | D7: Tunis, Tunisia | E7: 10–49 (Clutch) | F7: 74 | G7: =IF(F7>='Read me'!$B$12,"A",IF(F7>='Read me'!$B$13,"B","C")) -> B | H7: Nearshore teams delivering Java/JS for EU clients need proof of code quality and security; RevIA adds a CI quality gate + SARIF reports, in French, cheaper than CodeRabbit/Copilot seats, self-hostable for client NDAs. | I7: CTO / Delivery or Quality manager | J7: Team plan + CI, 30-day pilot on one project | K7: Staff augmentation: code quality proof for clients.
A8: 7 | B8: ZETA-BOX | C8: Software firms – Tunisia | D8: Sfax, Tunisia | E8: 10–49 (Clutch) | F8: 74 | G8: =IF(F8>='Read me'!$B$12,"A",IF(F8>='Read me'!$B$13,"B","C")) -> B | H8: Nearshore teams delivering Java/JS for EU clients need proof of code quality and security; RevIA adds a CI quality gate + SARIF reports, in French, cheaper than CodeRabbit/Copilot seats, self-hostable for client NDAs. | I8: CTO / Delivery or Quality manager | J8: Team plan + CI, 30-day pilot on one project
A9: 8 | B9: OpenClassrooms | C9: Education (schools & bootcamps) | D9: Paris, France (online) | E9: Online school, large | F9: 72 | G9: =IF(F9>='Read me'!$B$12,"A",IF(F9>='Read me'!$B$13,"B","C")) -> B | H9: Teaches secure coding & code review: RevIA gives every student an instant senior-style review (OWASP, fixes explained) at a per-seat price far below US tools; French + English; can self-host on campus. | I9: Head of studies / pedagogy lead, IT dept head | J9: Campus licence (self-hosted, unlimited students) or €2–3/student/semester | K9: Mentor-reviewed projects at scale: AI pre-review saves mentor time.
A10: 9 | B10: YouCode | C10: Education (schools & bootcamps) | D10: Youssoufia / Safi, Morocco | E10: Free coding school | F10: 72 | G10: =IF(F10>='Read me'!$B$12,"A",IF(F10>='Read me'!$B$13,"B","C")) -> B | H10: Teaches secure coding & code review: RevIA gives every student an instant senior-style review (OWASP, fixes explained) at a per-seat price far below US tools; French + English; can self-host on campus. | I10: Head of studies / pedagogy lead, IT dept head | J10: Campus licence (self-hosted, unlimited students) or €2–3/student/semester | K10: Simplon/UM6P-backed coding school.
A11: 10 | B11: Satoripop | C11: Software firms – Tunisia | D11: Sousse, Tunisia | E11: 50–249 (Clutch) | F11: 72 | G11: =IF(F11>='Read me'!$B$12,"A",IF(F11>='Read me'!$B$13,"B","C")) -> B | H11: Nearshore teams delivering Java/JS for EU clients need proof of code quality and security; RevIA adds a CI quality gate + SARIF reports, in French, cheaper than CodeRabbit/Copilot seats, self-hostable for client NDAs. | I11: CTO / Delivery or Quality manager | J11: Team plan + CI, 30-day pilot on one project | K11: Source: clutch.co/tn, themanifest.com
A12: 11 | B12: Softylines | C12: Software firms – Tunisia | D12: Sousse, Tunisia | E12: 50–249 (Clutch) | F12: 72 | G12: =IF(F12>='Read me'!$B$12,"A",IF(F12>='Read me'!$B$13,"B","C")) -> B | H12: Nearshore teams delivering Java/JS for EU clients need proof of code quality and security; RevIA adds a CI quality gate + SARIF reports, in French, cheaper than CodeRabbit/Copilot seats, self-hostable for client NDAs. | I12: CTO / Delivery or Quality manager | J12: Team plan + CI, 30-day pilot on one project | K12: Microservices + web/mobile delivery.
A13: 12 | B13: STEPS | C13: Software firms – Tunisia | D13: La Goulette, Tunisia | E13: 10–49 (Clutch) | F13: 72 | G13: =IF(F13>='Read me'!$B$12,"A",IF(F13>='Read me'!$B$13,"B","C")) -> B | H13: Nearshore teams delivering Java/JS for EU clients need proof of code quality and security; RevIA adds a CI quality gate + SARIF reports, in French, cheaper than CodeRabbit/Copilot seats, self-hostable for client NDAs. | I13: CTO / Delivery or Quality manager | J13: Team plan + CI, 30-day pilot on one project | K13: Also offers application testing.
A14: 13 | B14: Mss Group | C14: Software firms – Tunisia | D14: Tunis, Tunisia | E14: 10–49 (Clutch) | F14: 72 | G14: =IF(F14>='Read me'!$B$12,"A",IF(F14>='Read me'!$B$13,"B","C")) -> B | H14: Nearshore teams delivering Java/JS for EU clients need proof of code quality and security; RevIA adds a CI quality gate + SARIF reports, in French, cheaper than CodeRabbit/Copilot seats, self-hostable for client NDAs. | I14: CTO / Delivery or Quality manager | J14: Team plan + CI, 30-day pilot on one project | K14: DevOps + microservices: CI gate fits.
A15: 14 | B15: 42 Paris | C15: Education (schools & bootcamps) | D15: Paris, France | E15: 42 Network campus | F15: 70 | G15: =IF(F15>='Read me'!$B$12,"A",IF(F15>='Read me'!$B$13,"B","C")) -> B | H15: Teaches secure coding & code review: RevIA gives every student an instant senior-style review (OWASP, fixes explained) at a per-seat price far below US tools; French + English; can self-host on campus. | I15: Head of studies / pedagogy lead, IT dept head | J15: Campus licence (self-hosted, unlimited students) or €2–3/student/semester | K15: Peer evaluation culture; large student base.
A16: 15 | B16: INSAT (Institut National des Sciences Appliquées et de Technologie) | C16: Education (schools & bootcamps) | D16: Tunis, Tunisia | E16: Public engineering school | F16: 70 | G16: =IF(F16>='Read me'!$B$12,"A",IF(F16>='Read me'!$B$13,"B","C")) -> B | H16: Teaches secure coding & code review: RevIA gives every student an instant senior-style review (OWASP, fixes explained) at a per-seat price far below US tools; French + English; can self-host on campus. | I16: Head of studies / pedagogy lead, IT dept head | J16: Campus licence (self-hosted, unlimited students) or €2–3/student/semester | K16: Public: budget via department / projects.
A17: 16 | B17: ENSI (École Nationale des Sciences de l'Informatique) | C17: Education (schools & bootcamps) | D17: Manouba, Tunisia | E17: Public engineering school | F17: 70 | G17: =IF(F17>='Read me'!$B$12,"A",IF(F17>='Read me'!$B$13,"B","C")) -> B | H17: Teaches secure coding & code review: RevIA gives every student an instant senior-style review (OWASP, fixes explained) at a per-seat price far below US tools; French + English; can self-host on campus. | I17: Head of studies / pedagogy lead, IT dept head | J17: Campus licence (self-hosted, unlimited students) or €2–3/student/semester | K17: CS-focused engineering school.
A18: 17 | B18: TEK-UP University | C18: Education (schools & bootcamps) | D18: Tunis, Tunisia | E18: Private university | F18: 70 | G18: =IF(F18>='Read me'!$B$12,"A",IF(F18>='Read me'!$B$13,"B","C")) -> B | H18: Teaches secure coding & code review: RevIA gives every student an instant senior-style review (OWASP, fixes explained) at a per-seat price far below US tools; French + English; can self-host on campus. | I18: Head of studies / pedagogy lead, IT dept head | J18: Campus licence (self-hosted, unlimited students) or €2–3/student/semester
A19: 18 | B19: Orange Digital Center Tunisia (coding school) | C19: Education (schools & bootcamps) | D19: Tunis, Tunisia | E19: Free coding school | F19: 70 | G19: =IF(F19>='Read me'!$B$12,"A",IF(F19>='Read me'!$B$13,"B","C")) -> B | H19: Teaches secure coding & code review: RevIA gives every student an instant senior-style review (OWASP, fixes explained) at a per-seat price far below US tools; French + English; can self-host on campus. | I19: Head of studies / pedagogy lead, IT dept head | J19: Campus licence (self-hosted, unlimited students) or €2–3/student/semester | K19: Free trainings: campus licence / sponsorship angle.
A20: 19 | B20: Moneycore Smart | C20: Software firms – Tunisia | D20: Tunis, Tunisia | E20: 50–249 (Clutch) | F20: 70 | G20: =IF(F20>='Read me'!$B$12,"A",IF(F20>='Read me'!$B$13,"B","C")) -> B | H20: Nearshore teams delivering Java/JS for EU clients need proof of code quality and security; RevIA adds a CI quality gate + SARIF reports, in French, cheaper than CodeRabbit/Copilot seats, self-hostable for client NDAs. | I20: CTO / Delivery or Quality manager | J20: Team plan + CI, 30-day pilot on one project | K20: Lists cybersecurity among services → can resell.
A21: 20 | B21: Le Backyard | C21: Software firms – Tunisia | D21: Tunis, Tunisia | E21: 10–49 (Clutch) | F21: 70 | G21: =IF(F21>='Read me'!$B$12,"A",IF(F21>='Read me'!$B$13,"B","C")) -> B | H21: Nearshore teams delivering Java/JS for EU clients need proof of code quality and security; RevIA adds a CI quality gate + SARIF reports, in French, cheaper than CodeRabbit/Copilot seats, self-hostable for client NDAs. | I21: CTO / Delivery or Quality manager | J21: Team plan + CI, 30-day pilot on one project
A22: 21 | B22: Navinspire IA | C22: Software firms – Tunisia | D22: Tunis, Tunisia | E22: 10–49 (Clutch) | F22: 70 | G22: =IF(F22>='Read me'!$B$12,"A",IF(F22>='Read me'!$B$13,"B","C")) -> B | H22: Nearshore teams delivering Java/JS for EU clients need proof of code quality and security; RevIA adds a CI quality gate + SARIF reports, in French, cheaper than CodeRabbit/Copilot seats, self-hostable for client NDAs. | I22: CTO / Delivery or Quality manager | J22: Team plan + CI, 30-day pilot on one project | K22: AI-native team, quick adopter.
A23: 22 | B23: WOLFNOVA | C23: Software firms – Tunisia | D23: Ariana, Tunisia | E23: 10–49 (Clutch) | F23: 70 | G23: =IF(F23>='Read me'!$B$12,"A",IF(F23>='Read me'!$B$13,"B","C")) -> B | H23: Nearshore teams delivering Java/JS for EU clients need proof of code quality and security; RevIA adds a CI quality gate + SARIF reports, in French, cheaper than CodeRabbit/Copilot seats, self-hostable for client NDAs. | I23: CTO / Delivery or Quality manager | J23: Team plan + CI, 30-day pilot on one project
A24: 23 | B24: OwTalent | C24: Software firms – Tunisia | D24: Sfax, Tunisia | E24: 10–49 (Clutch) | F24: 70 | G24: =IF(F24>='Read me'!$B$12,"A",IF(F24>='Read me'!$B$13,"B","C")) -> B | H24: Nearshore teams delivering Java/JS for EU clients need proof of code quality and security; RevIA adds a CI quality gate + SARIF reports, in French, cheaper than CodeRabbit/Copilot seats, self-hostable for client NDAs. | I24: CTO / Delivery or Quality manager | J24: Team plan + CI, 30-day pilot on one project | K24: Also offers application testing.
A25: 24 | B25: ostrix | C25: Software firms – Tunisia | D25: Hammam Sousse, Tunisia | E25: 10–49 (Clutch) | F25: 70 | G25: =IF(F25>='Read me'!$B$12,"A",IF(F25>='Read me'!$B$13,"B","C")) -> B | H25: Nearshore teams delivering Java/JS for EU clients need proof of code quality and security; RevIA adds a CI quality gate + SARIF reports, in French, cheaper than CodeRabbit/Copilot seats, self-hostable for client NDAs. | I25: CTO / Delivery or Quality manager | J25: Team plan + CI, 30-day pilot on one project
A26: 25 | B26: Vynesus | C26: Software firms – Tunisia | D26: Hammam Sousse, Tunisia | E26: 10–49 (Clutch) | F26: 70 | G26: =IF(F26>='Read me'!$B$12,"A",IF(F26>='Read me'!$B$13,"B","C")) -> B | H26: Nearshore teams delivering Java/JS for EU clients need proof of code quality and security; RevIA adds a CI quality gate + SARIF reports, in French, cheaper than CodeRabbit/Copilot seats, self-hostable for client NDAs. | I26: CTO / Delivery or Quality manager | J26: Team plan + CI, 30-day pilot on one project | K26: Also offers application testing.
A27: 26 | B27: xHub | C27: Software firms – Morocco | D27: Casablanca, Morocco | E27: 50–249 (GoodFirms) | F27: 70 | G27: =IF(F27>='Read me'!$B$12,"A",IF(F27>='Read me'!$B$13,"B","C")) -> B | H27: Offshore/nearshore delivery for French-speaking clients; same quality-gate and SARIF evidence need; French UI and self-hosting help with client confidentiality clauses. | I27: CTO / Delivery manager | J27: Team plan + CI, 30-day pilot | K27: Source: goodfirms.co Morocco directory
A28: 27 | B28: Le Wagon | C28: Education (schools & bootcamps) | D28: Paris + global campuses | E28: Global bootcamp | F28: 68 | G28: =IF(F28>='Read me'!$B$12,"A",IF(F28>='Read me'!$B$13,"B","C")) -> B | H28: Teaches secure coding & code review: RevIA gives every student an instant senior-style review (OWASP, fixes explained) at a per-seat price far below US tools; French + English; can self-host on campus. | I28: Head of studies / pedagogy lead, IT dept head | J28: Campus licence (self-hosted, unlimited students) or €2–3/student/semester | K28: Web dev bootcamp, FR/EN.
A29: 28 | B29: O'clock | C29: Education (schools & bootcamps) | D29: France (remote) | E29: Remote bootcamp | F29: 68 | G29: =IF(F29>='Read me'!$B$12,"A",IF(F29>='Read me'!$B$13,"B","C")) -> B | H29: Teaches secure coding & code review: RevIA gives every student an instant senior-style review (OWASP, fixes explained) at a per-seat price far below US tools; French + English; can self-host on campus. | I29: Head of studies / pedagogy lead, IT dept head | J29: Campus licence (self-hosted, unlimited students) or €2–3/student/semester | K29: Remote cohorts → automated review is valuable.
A30: 29 | B30: Institut International de Technologie (IIT) | C30: Education (schools & bootcamps) | D30: Sfax, Tunisia | E30: Private engineering school | F30: 68 | G30: =IF(F30>='Read me'!$B$12,"A",IF(F30>='Read me'!$B$13,"B","C")) -> B | H30: Teaches secure coding & code review: RevIA gives every student an instant senior-style review (OWASP, fixes explained) at a per-seat price far below US tools; French + English; can self-host on campus. | I30: Head of studies / pedagogy lead, IT dept head | J30: Campus licence (self-hosted, unlimited students) or €2–3/student/semester
A31: 30 | B31: MedTech – South Mediterranean University | C31: Education (schools & bootcamps) | D31: Tunis, Tunisia | E31: Private engineering school | F31: 68 | G31: =IF(F31>='Read me'!$B$12,"A",IF(F31>='Read me'!$B$13,"B","C")) -> B | H31: Teaches secure coding & code review: RevIA gives every student an instant senior-style review (OWASP, fixes explained) at a per-seat price far below US tools; French + English; can self-host on campus. | I31: Head of studies / pedagogy lead, IT dept head | J31: Campus licence (self-hosted, unlimited students) or €2–3/student/semester | K31: English-taught programmes.
A32: 31 | B32: EMSI | C32: Education (schools & bootcamps) | D32: Casablanca + other cities, Morocco | E32: Private engineering school | F32: 68 | G32: =IF(F32>='Read me'!$B$12,"A",IF(F32>='Read me'!$B$13,"B","C")) -> B | H32: Teaches secure coding & code review: RevIA gives every student an instant senior-style review (OWASP, fixes explained) at a per-seat price far below US tools; French + English; can self-host on campus. | I32: Head of studies / pedagogy lead, IT dept head | J32: Campus licence (self-hosted, unlimited students) or €2–3/student/semester
A33: 32 | B33: Proxym Group | C33: Software firms – Tunisia | D33: Sousse/Tunis, Tunisia | E33: Mid-size | F33: 68 | G33: =IF(F33>='Read me'!$B$12,"A",IF(F33>='Read me'!$B$13,"B","C")) -> B | H33: Nearshore teams delivering Java/JS for EU clients need proof of code quality and security; RevIA adds a CI quality gate + SARIF reports, in French, cheaper than CodeRabbit/Copilot seats, self-hostable for client NDAs. | I33: CTO / Delivery or Quality manager | J33: Team plan + CI, 30-day pilot on one project | K33: Mobile/web delivery for EU clients.
A34: 33 | B34: Softtodo | C34: Software firms – Tunisia | D34: Sfax, Tunisia | E34: 10–49 (Clutch) | F34: 68 | G34: =IF(F34>='Read me'!$B$12,"A",IF(F34>='Read me'!$B$13,"B","C")) -> B | H34: Nearshore teams delivering Java/JS for EU clients need proof of code quality and security; RevIA adds a CI quality gate + SARIF reports, in French, cheaper than CodeRabbit/Copilot seats, self-hostable for client NDAs. | I34: CTO / Delivery or Quality manager | J34: Team plan + CI, 30-day pilot on one project
A35: 34 | B35: UTEEK | C35: Software firms – Tunisia | D35: Tunis, Tunisia | E35: 10–49 (Clutch) | F35: 68 | G35: =IF(F35>='Read me'!$B$12,"A",IF(F35>='Read me'!$B$13,"B","C")) -> B | H35: Nearshore teams delivering Java/JS for EU clients need proof of code quality and security; RevIA adds a CI quality gate + SARIF reports, in French, cheaper than CodeRabbit/Copilot seats, self-hostable for client NDAs. | I35: CTO / Delivery or Quality manager | J35: Team plan + CI, 30-day pilot on one project
A36: 35 | B36: deadLine | C36: Software firms – Morocco | D36: Casablanca, Morocco | E36: 10–49 (GoodFirms) | F36: 68 | G36: =IF(F36>='Read me'!$B$12,"A",IF(F36>='Read me'!$B$13,"B","C")) -> B | H36: Offshore/nearshore delivery for French-speaking clients; same quality-gate and SARIF evidence need; French UI and self-hosting help with client confidentiality clauses. | I36: CTO / Delivery manager | J36: Team plan + CI, 30-day pilot
A37: 36 | B37: Taillis Labs | C37: Software firms – Morocco | D37: Casablanca, Morocco | E37: 10–49 (GoodFirms) | F37: 68 | G37: =IF(F37>='Read me'!$B$12,"A",IF(F37>='Read me'!$B$13,"B","C")) -> B | H37: Offshore/nearshore delivery for French-speaking clients; same quality-gate and SARIF evidence need; French UI and self-hosting help with client confidentiality clauses. | I37: CTO / Delivery manager | J37: Team plan + CI, 30-day pilot
A38: 37 | B38: Evold | C38: Software firms – Morocco | D38: Rabat, Morocco | E38: 10–49 (GoodFirms) | F38: 68 | G38: =IF(F38>='Read me'!$B$12,"A",IF(F38>='Read me'!$B$13,"B","C")) -> B | H38: Offshore/nearshore delivery for French-speaking clients; same quality-gate and SARIF evidence need; French UI and self-hosting help with client confidentiality clauses. | I38: CTO / Delivery manager | J38: Team plan + CI, 30-day pilot
A39: 38 | B39: Ada Tech School | C39: Education (schools & bootcamps) | D39: Paris, France | E39: Bootcamp | F39: 66 | G39: =IF(F39>='Read me'!$B$12,"A",IF(F39>='Read me'!$B$13,"B","C")) -> B | H39: Teaches secure coding & code review: RevIA gives every student an instant senior-style review (OWASP, fixes explained) at a per-seat price far below US tools; French + English; can self-host on campus. | I39: Head of studies / pedagogy lead, IT dept head | J39: Campus licence (self-hosted, unlimited students) or €2–3/student/semester | K39: Inclusive dev school.
A40: 39 | B40: Epitech | C40: Education (schools & bootcamps) | D40: France (multiple campuses) | E40: Large private school | F40: 66 | G40: =IF(F40>='Read me'!$B$12,"A",IF(F40>='Read me'!$B$13,"B","C")) -> B | H40: Teaches secure coding & code review: RevIA gives every student an instant senior-style review (OWASP, fixes explained) at a per-seat price far below US tools; French + English; can self-host on campus. | I40: Head of studies / pedagogy lead, IT dept head | J40: Campus licence (self-hosted, unlimited students) or €2–3/student/semester | K40: Project-based pedagogy.
A41: 40 | B41: Zone01 Normandie | C41: Education (schools & bootcamps) | D41: Rouen, France | E41: Peer-learning coding school | F41: 66 | G41: =IF(F41>='Read me'!$B$12,"A",IF(F41>='Read me'!$B$13,"B","C")) -> B | H41: Teaches secure coding & code review: RevIA gives every student an instant senior-style review (OWASP, fixes explained) at a per-seat price far below US tools; French + English; can self-host on campus. | I41: Head of studies / pedagogy lead, IT dept head | J41: Campus licence (self-hosted, unlimited students) or €2–3/student/semester
A42: 41 | B42: Wevioo | C42: Software firms – Tunisia | D42: Tunis, Tunisia | E42: Mid-size | F42: 66 | G42: =IF(F42>='Read me'!$B$12,"A",IF(F42>='Read me'!$B$13,"B","C")) -> B | H42: Nearshore teams delivering Java/JS for EU clients need proof of code quality and security; RevIA adds a CI quality gate + SARIF reports, in French, cheaper than CodeRabbit/Copilot seats, self-hostable for client NDAs. | I42: CTO / Delivery or Quality manager | J42: Team plan + CI, 30-day pilot on one project
A43: 42 | B43: Cynapsys | C43: Software firms – Tunisia | D43: Tunis, Tunisia | E43: Mid-size | F43: 66 | G43: =IF(F43>='Read me'!$B$12,"A",IF(F43>='Read me'!$B$13,"B","C")) -> B | H43: Nearshore teams delivering Java/JS for EU clients need proof of code quality and security; RevIA adds a CI quality gate + SARIF reports, in French, cheaper than CodeRabbit/Copilot seats, self-hostable for client NDAs. | I43: CTO / Delivery or Quality manager | J43: Team plan + CI, 30-day pilot on one project
A44: 43 | B44: Medianet | C44: Software firms – Tunisia | D44: Tunis, Tunisia | E44: Web agency | F44: 66 | G44: =IF(F44>='Read me'!$B$12,"A",IF(F44>='Read me'!$B$13,"B","C")) -> B | H44: Nearshore teams delivering Java/JS for EU clients need proof of code quality and security; RevIA adds a CI quality gate + SARIF reports, in French, cheaper than CodeRabbit/Copilot seats, self-hostable for client NDAs. | I44: CTO / Delivery or Quality manager | J44: Team plan + CI, 30-day pilot on one project | K44: PHP/JS web projects.
A45: 44 | B45: Norsys Afrique | C45: Software firms – Morocco | D45: Marrakech, Morocco | E45: Mid-size Java ESN | F45: 66 | G45: =IF(F45>='Read me'!$B$12,"A",IF(F45>='Read me'!$B$13,"B","C")) -> B | H45: Offshore/nearshore delivery for French-speaking clients; same quality-gate and SARIF evidence need; French UI and self-hosting help with client confidentiality clauses. | I45: CTO / Delivery manager | J45: Team plan + CI, 30-day pilot | K45: Java-oriented nearshore of French ESN Norsys.
A46: 45 | B46: FLEXIAPPS | C46: Software firms – Morocco | D46: Rabat, Morocco | E46: 10–49 (GoodFirms) | F46: 66 | G46: =IF(F46>='Read me'!$B$12,"A",IF(F46>='Read me'!$B$13,"B","C")) -> B | H46: Offshore/nearshore delivery for French-speaking clients; same quality-gate and SARIF evidence need; French UI and self-hosting help with client confidentiality clauses. | I46: CTO / Delivery manager | J46: Team plan + CI, 30-day pilot
A47: 46 | B47: YANVISION | C47: Software firms – Morocco | D47: Casablanca, Morocco | E47: 10–49 (GoodFirms) | F47: 66 | G47: =IF(F47>='Read me'!$B$12,"A",IF(F47>='Read me'!$B$13,"B","C")) -> B | H47: Offshore/nearshore delivery for French-speaking clients; same quality-gate and SARIF evidence need; French UI and self-hosting help with client confidentiality clauses. | I47: CTO / Delivery manager | J47: Team plan + CI, 30-day pilot
A48: 47 | B48: Takima | C48: Java/Spring consultancies – France | D48: Paris, France | E48: Java-focused consultancy | F48: 66 | G48: =IF(F48>='Read me'!$B$12,"A",IF(F48>='Read me'!$B$13,"B","C")) -> B | H48: Java/Spring-heavy consultancy: can resell or embed RevIA in delivery (code audits, quality gates) and self-host it for clients who refuse SaaS code tools. | I48: Practice lead Java / Craft & quality lead | J48: Reseller / white-label + self-hosted licence
A49: 48 | B49: Volkeno | C49: Software firms – West/Sub-Saharan Africa | D49: Dakar, Senegal | E49: Dev agency & training | F49: 66 | G49: =IF(F49>='Read me'!$B$12,"A",IF(F49>='Read me'!$B$13,"B","C")) -> B | H49: Growing dev teams with limited budget for US-priced tools; free tier + low per-dev price + local LLM option fit well. | I49: CTO / Head of engineering | J49: Free → Pro, startup discount | K49: Also trains developers → double use.
A50: 49 | B50: ESIEA | C50: Education (schools & bootcamps) | D50: Paris / Laval, France | E50: Engineering school | F50: 64 | G50: =IF(F50>='Read me'!$B$12,"A",IF(F50>='Read me'!$B$13,"B","C")) -> B | H50: Teaches secure coding & code review: RevIA gives every student an instant senior-style review (OWASP, fixes explained) at a per-seat price far below US tools; French + English; can self-host on campus. | I50: Head of studies / pedagogy lead, IT dept head | J50: Campus licence (self-hosted, unlimited students) or €2–3/student/semester | K50: Strong cybersecurity focus.
A51: 50 | B51: ENSIAS | C51: Education (schools & bootcamps) | D51: Rabat, Morocco | E51: Public engineering school | F51: 64 | G51: =IF(F51>='Read me'!$B$12,"A",IF(F51>='Read me'!$B$13,"B","C")) -> B | H51: Teaches secure coding & code review: RevIA gives every student an instant senior-style review (OWASP, fixes explained) at a per-seat price far below US tools; French + English; can self-host on campus. | I51: Head of studies / pedagogy lead, IT dept head | J51: Campus licence (self-hosted, unlimited students) or €2–3/student/semester
A52: 51 | B52: Teamwill | C52: Software firms – Tunisia | D52: Tunis, Tunisia | E52: Mid-size | F52: 64 | G52: =IF(F52>='Read me'!$B$12,"A",IF(F52>='Read me'!$B$13,"B","C")) -> B | H52: Nearshore teams delivering Java/JS for EU clients need proof of code quality and security; RevIA adds a CI quality gate + SARIF reports, in French, cheaper than CodeRabbit/Copilot seats, self-hostable for client NDAs. | I52: CTO / Delivery or Quality manager | J52: Team plan + CI, 30-day pilot on one project | K52: Leasing/finance software consulting.
A53: 52 | B53: BFI Group | C53: Software firms – Tunisia | D53: Tunis, Tunisia | E53: Mid-size banking software | F53: 64 | G53: =IF(F53>='Read me'!$B$12,"A",IF(F53>='Read me'!$B$13,"B","C")) -> B | H53: Nearshore teams delivering Java/JS for EU clients need proof of code quality and security; RevIA adds a CI quality gate + SARIF reports, in French, cheaper than CodeRabbit/Copilot seats, self-hostable for client NDAs. | I53: CTO / Delivery or Quality manager | J53: Team plan + CI, 30-day pilot on one project | K53: Banking software → security audit evidence.
A54: 53 | B54: Qartivus Technologies | C54: Software firms – Tunisia | D54: Sfax, Tunisia | E54: 2–9 (Clutch) | F54: 64 | G54: =IF(F54>='Read me'!$B$12,"A",IF(F54>='Read me'!$B$13,"B","C")) -> B | H54: Nearshore teams delivering Java/JS for EU clients need proof of code quality and security; RevIA adds a CI quality gate + SARIF reports, in French, cheaper than CodeRabbit/Copilot seats, self-hostable for client NDAs. | I54: CTO / Delivery or Quality manager | J54: Team plan + CI, 30-day pilot on one project | K54: DevOps + testing services.
A55: 54 | B55: Ippon Technologies | C55: Java/Spring consultancies – France | D55: Paris, France | E55: Mid-size Java/cloud consultancy | F55: 64 | G55: =IF(F55>='Read me'!$B$12,"A",IF(F55>='Read me'!$B$13,"B","C")) -> B | H55: Java/Spring-heavy consultancy: can resell or embed RevIA in delivery (code audits, quality gates) and self-host it for clients who refuse SaaS code tools. | I55: Practice lead Java / Craft & quality lead | J55: Reseller / white-label + self-hosted licence | K55: Java/Spring DNA.
A56: 55 | B56: Smile | C56: Java/Spring consultancies – France | D56: Paris, France | E56: Open-source integrator | F56: 64 | G56: =IF(F56>='Read me'!$B$12,"A",IF(F56>='Read me'!$B$13,"B","C")) -> B | H56: Java/Spring-heavy consultancy: can resell or embed RevIA in delivery (code audits, quality gates) and self-host it for clients who refuse SaaS code tools. | I56: Practice lead Java / Craft & quality lead | J56: Reseller / white-label + self-hosted licence | K56: Open-source/self-hosted culture.
A57: 56 | B57: Norsys | C57: Java/Spring consultancies – France | D57: Lille, France | E57: Java ESN | F57: 64 | G57: =IF(F57>='Read me'!$B$12,"A",IF(F57>='Read me'!$B$13,"B","C")) -> B | H57: Java/Spring-heavy consultancy: can resell or embed RevIA in delivery (code audits, quality gates) and self-host it for clients who refuse SaaS code tools. | I57: Practice lead Java / Craft & quality lead | J57: Reseller / white-label + self-hosted licence | K57: Java/craftsmanship focus.
A58: 57 | B58: Ironhack Paris | C58: Education (schools & bootcamps) | D58: Paris, France | E58: Bootcamp | F58: 62 | G58: =IF(F58>='Read me'!$B$12,"A",IF(F58>='Read me'!$B$13,"B","C")) -> B | H58: Teaches secure coding & code review: RevIA gives every student an instant senior-style review (OWASP, fixes explained) at a per-seat price far below US tools; French + English; can self-host on campus. | I58: Head of studies / pedagogy lead, IT dept head | J58: Campus licence (self-hosted, unlimited students) or €2–3/student/semester | K58: Global bootcamp, English-first.
A59: 58 | B59: EPITA | C59: Education (schools & bootcamps) | D59: Paris, France | E59: Engineering school | F59: 62 | G59: =IF(F59>='Read me'!$B$12,"A",IF(F59>='Read me'!$B$13,"B","C")) -> B | H59: Teaches secure coding & code review: RevIA gives every student an instant senior-style review (OWASP, fixes explained) at a per-seat price far below US tools; French + English; can self-host on campus. | I59: Head of studies / pedagogy lead, IT dept head | J59: Campus licence (self-hosted, unlimited students) or €2–3/student/semester | K59: Security track (SRS).
A60: 59 | B60: SUP'COM | C60: Education (schools & bootcamps) | D60: Ariana, Tunisia | E60: Public engineering school | F60: 62 | G60: =IF(F60>='Read me'!$B$12,"A",IF(F60>='Read me'!$B$13,"B","C")) -> B | H60: Teaches secure coding & code review: RevIA gives every student an instant senior-style review (OWASP, fixes explained) at a per-seat price far below US tools; French + English; can self-host on campus. | I60: Head of studies / pedagogy lead, IT dept head | J60: Campus licence (self-hosted, unlimited students) or €2–3/student/semester | K60: Telecom/IT engineering.
A61: 60 | B61: OXIA | C61: Software firms – Tunisia | D61: Tunis, Tunisia | E61: Mid-size ESN | F61: 62 | G61: =IF(F61>='Read me'!$B$12,"A",IF(F61>='Read me'!$B$13,"B","C")) -> B | H61: Nearshore teams delivering Java/JS for EU clients need proof of code quality and security; RevIA adds a CI quality gate + SARIF reports, in French, cheaper than CodeRabbit/Copilot seats, self-hostable for client NDAs. | I61: CTO / Delivery or Quality manager | J61: Team plan + CI, 30-day pilot on one project
A62: 61 | B62: Dot-it | C62: Software firms – Tunisia | D62: Tunis, Tunisia | E62: Software house | F62: 62 | G62: =IF(F62>='Read me'!$B$12,"A",IF(F62>='Read me'!$B$13,"B","C")) -> B | H62: Nearshore teams delivering Java/JS for EU clients need proof of code quality and security; RevIA adds a CI quality gate + SARIF reports, in French, cheaper than CodeRabbit/Copilot seats, self-hostable for client NDAs. | I62: CTO / Delivery or Quality manager | J62: Team plan + CI, 30-day pilot on one project
A63: 62 | B63: Tritux | C63: Software firms – Tunisia | D63: Tunis, Tunisia | E63: Software house | F63: 62 | G63: =IF(F63>='Read me'!$B$12,"A",IF(F63>='Read me'!$B$13,"B","C")) -> B | H63: Nearshore teams delivering Java/JS for EU clients need proof of code quality and security; RevIA adds a CI quality gate + SARIF reports, in French, cheaper than CodeRabbit/Copilot seats, self-hostable for client NDAs. | I63: CTO / Delivery or Quality manager | J63: Team plan + CI, 30-day pilot on one project
A64: 63 | B64: Avaxia Group | C64: Software firms – Tunisia | D64: Tunis, Tunisia | E64: Mid-size ESN | F64: 62 | G64: =IF(F64>='Read me'!$B$12,"A",IF(F64>='Read me'!$B$13,"B","C")) -> B | H64: Nearshore teams delivering Java/JS for EU clients need proof of code quality and security; RevIA adds a CI quality gate + SARIF reports, in French, cheaper than CodeRabbit/Copilot seats, self-hostable for client NDAs. | I64: CTO / Delivery or Quality manager | J64: Team plan + CI, 30-day pilot on one project
A65: 64 | B65: Zenika | C65: Java/Spring consultancies – France | D65: Paris, France | E65: Mid-size consultancy | F65: 62 | G65: =IF(F65>='Read me'!$B$12,"A",IF(F65>='Read me'!$B$13,"B","C")) -> B | H65: Java/Spring-heavy consultancy: can resell or embed RevIA in delivery (code audits, quality gates) and self-host it for clients who refuse SaaS code tools. | I65: Practice lead Java / Craft & quality lead | J65: Reseller / white-label + self-hosted licence | K65: Historic SpringSource partner (blog.zenika.com).
A66: 65 | B66: Younup | C66: Java/Spring consultancies – France | D66: Nantes, France | E66: Consultancy | F66: 62 | G66: =IF(F66>='Read me'!$B$12,"A",IF(F66>='Read me'!$B$13,"B","C")) -> B | H66: Java/Spring-heavy consultancy: can resell or embed RevIA in delivery (code audits, quality gates) and self-host it for clients who refuse SaaS code tools. | I66: Practice lead Java / Craft & quality lead | J66: Reseller / white-label + self-hosted licence
A67: 66 | B67: ALX Africa | C67: Education (schools & bootcamps) | D67: Pan-African (online) | E67: Very large online programme | F67: 60 | G67: =IF(F67>='Read me'!$B$12,"A",IF(F67>='Read me'!$B$13,"B","C")) -> B | H67: Teaches secure coding & code review: RevIA gives every student an instant senior-style review (OWASP, fixes explained) at a per-seat price far below US tools; French + English; can self-host on campus. | I67: Head of studies / pedagogy lead, IT dept head | J67: Campus licence (self-hosted, unlimited students) or €2–3/student/semester | K67: English; scale means a big deal but slow procurement.
A68: 67 | B68: Focus Corporation | C68: Software firms – Tunisia | D68: Tunis, Tunisia | E68: Mid-size | F68: 60 | G68: =IF(F68>='Read me'!$B$12,"A",IF(F68>='Read me'!$B$13,"B","C")) -> B | H68: Nearshore teams delivering Java/JS for EU clients need proof of code quality and security; RevIA adds a CI quality gate + SARIF reports, in French, cheaper than CodeRabbit/Copilot seats, self-hostable for client NDAs. | I68: CTO / Delivery or Quality manager | J68: Team plan + CI, 30-day pilot on one project
A69: 68 | B69: Kaisens Data | C69: Software firms – Tunisia | D69: Tunis / Paris | E69: Mid-size | F69: 60 | G69: =IF(F69>='Read me'!$B$12,"A",IF(F69>='Read me'!$B$13,"B","C")) -> B | H69: Nearshore teams delivering Java/JS for EU clients need proof of code quality and security; RevIA adds a CI quality gate + SARIF reports, in French, cheaper than CodeRabbit/Copilot seats, self-hostable for client NDAs. | I69: CTO / Delivery or Quality manager | J69: Team plan + CI, 30-day pilot on one project | K69: Data & dev services FR/TN.
A70: 69 | B70: Global Performance Business Services | C70: Software firms – Morocco | D70: Casablanca, Morocco | E70: 10–49 (GoodFirms) | F70: 60 | G70: =IF(F70>='Read me'!$B$12,"A",IF(F70>='Read me'!$B$13,"B","C")) -> B | H70: Offshore/nearshore delivery for French-speaking clients; same quality-gate and SARIF evidence need; French UI and self-hosting help with client confidentiality clauses. | I70: CTO / Delivery manager | J70: Team plan + CI, 30-day pilot
A71: 70 | B71: SFEIR | C71: Java/Spring consultancies – France | D71: Paris, France | E71: Mid-size consultancy | F71: 60 | G71: =IF(F71>='Read me'!$B$12,"A",IF(F71>='Read me'!$B$13,"B","C")) -> B | H71: Java/Spring-heavy consultancy: can resell or embed RevIA in delivery (code audits, quality gates) and self-host it for clients who refuse SaaS code tools. | I71: Practice lead Java / Craft & quality lead | J71: Reseller / white-label + self-hosted licence
A72: 71 | B72: Klee Group | C72: Java/Spring consultancies – France | D72: Paris, France | E72: Software consultancy | F72: 60 | G72: =IF(F72>='Read me'!$B$12,"A",IF(F72>='Read me'!$B$13,"B","C")) -> B | H72: Java/Spring-heavy consultancy: can resell or embed RevIA in delivery (code audits, quality gates) and self-host it for clients who refuse SaaS code tools. | I72: Practice lead Java / Craft & quality lead | J72: Reseller / white-label + self-hosted licence
A73: 72 | B73: Flat6Labs Tunis | C73: Channel partners | D73: Tunis, Tunisia | E73: Startup accelerator | F73: 60 | G73: =IF(F73>='Read me'!$B$12,"A",IF(F73>='Read me'!$B$13,"B","C")) -> B | H73: Not an end buyer: a distribution partner that can put RevIA in front of many startups / dev teams at once. | I73: Program manager / partnerships | J73: Partner discount for portfolio companies | K73: Portfolio-wide startup deal.
A74: 73 | B74: ESI – École nationale Supérieure d'Informatique | C74: Education (schools & bootcamps) | D74: Algiers, Algeria | E74: Public engineering school | F74: 58 | G74: =IF(F74>='Read me'!$B$12,"A",IF(F74>='Read me'!$B$13,"B","C")) -> C | H74: Teaches secure coding & code review: RevIA gives every student an instant senior-style review (OWASP, fixes explained) at a per-seat price far below US tools; French + English; can self-host on campus. | I74: Head of studies / pedagogy lead, IT dept head | J74: Campus licence (self-hosted, unlimited students) or €2–3/student/semester
A75: 74 | B75: ESP – École Supérieure Polytechnique de Dakar | C75: Education (schools & bootcamps) | D75: Dakar, Senegal | E75: Public engineering school | F75: 58 | G75: =IF(F75>='Read me'!$B$12,"A",IF(F75>='Read me'!$B$13,"B","C")) -> C | H75: Teaches secure coding & code review: RevIA gives every student an instant senior-style review (OWASP, fixes explained) at a per-seat price far below US tools; French + English; can self-host on campus. | I75: Head of studies / pedagogy lead, IT dept head | J75: Campus licence (self-hosted, unlimited students) or €2–3/student/semester
A76: 75 | B76: Semicolon Africa | C76: Education (schools & bootcamps) | D76: Lagos, Nigeria | E76: Bootcamp | F76: 58 | G76: =IF(F76>='Read me'!$B$12,"A",IF(F76>='Read me'!$B$13,"B","C")) -> C | H76: Teaches secure coding & code review: RevIA gives every student an instant senior-style review (OWASP, fixes explained) at a per-seat price far below US tools; French + English; can self-host on campus. | I76: Head of studies / pedagogy lead, IT dept head | J76: Campus licence (self-hosted, unlimited students) or €2–3/student/semester | K76: English; Java track.
A77: 76 | B77: Integration Objects | C77: Software firms – Tunisia | D77: Tunis, Tunisia | E77: Mid-size industrial software | F77: 58 | G77: =IF(F77>='Read me'!$B$12,"A",IF(F77>='Read me'!$B$13,"B","C")) -> C | H77: Nearshore teams delivering Java/JS for EU clients need proof of code quality and security; RevIA adds a CI quality gate + SARIF reports, in French, cheaper than CodeRabbit/Copilot seats, self-hostable for client NDAs. | I77: CTO / Delivery or Quality manager | J77: Team plan + CI, 30-day pilot on one project
A78: 77 | B78: Theodo | C78: Java/Spring consultancies – France | D78: Paris, France | E78: Product studio | F78: 58 | G78: =IF(F78>='Read me'!$B$12,"A",IF(F78>='Read me'!$B$13,"B","C")) -> C | H78: Java/Spring-heavy consultancy: can resell or embed RevIA in delivery (code audits, quality gates) and self-host it for clients who refuse SaaS code tools. | I78: Practice lead Java / Craft & quality lead | J78: Reseller / white-label + self-hosted licence
A79: 78 | B79: Palo IT | C79: Java/Spring consultancies – France | D79: Paris, France | E79: Consultancy | F79: 58 | G79: =IF(F79>='Read me'!$B$12,"A",IF(F79>='Read me'!$B$13,"B","C")) -> C | H79: Java/Spring-heavy consultancy: can resell or embed RevIA in delivery (code audits, quality gates) and self-host it for clients who refuse SaaS code tools. | I79: Practice lead Java / Craft & quality lead | J79: Reseller / white-label + self-hosted licence | K79: Craft/agile positioning.
A80: 79 | B80: Moringa School | C80: Education (schools & bootcamps) | D80: Nairobi, Kenya | E80: Bootcamp | F80: 56 | G80: =IF(F80>='Read me'!$B$12,"A",IF(F80>='Read me'!$B$13,"B","C")) -> C | H80: Teaches secure coding & code review: RevIA gives every student an instant senior-style review (OWASP, fixes explained) at a per-seat price far below US tools; French + English; can self-host on campus. | I80: Head of studies / pedagogy lead, IT dept head | J80: Campus licence (self-hosted, unlimited students) or €2–3/student/semester | K80: English.
A81: 80 | B81: VERMEG | C81: Software firms – Tunisia | D81: Tunis, Tunisia (+ Brussels) | E81: 1,000–9,999 (Clutch) | F81: 56 | G81: =IF(F81>='Read me'!$B$12,"A",IF(F81>='Read me'!$B$13,"B","C")) -> C | H81: Nearshore teams delivering Java/JS for EU clients need proof of code quality and security; RevIA adds a CI quality gate + SARIF reports, in French, cheaper than CodeRabbit/Copilot seats, self-hostable for client NDAs. | I81: CTO / Delivery or Quality manager | J81: Team plan + CI, 30-day pilot on one project | K81: Financial software; large procurement → start with one team. Source: clutch.co/tn
A82: 81 | B82: SQLI Maroc | C82: Software firms – Morocco | D82: Rabat / Oujda, Morocco | E82: Nearshore centre | F82: 56 | G82: =IF(F82>='Read me'!$B$12,"A",IF(F82>='Read me'!$B$13,"B","C")) -> C | H82: Offshore/nearshore delivery for French-speaking clients; same quality-gate and SARIF evidence need; French UI and self-hosting help with client confidentiality clauses. | I82: CTO / Delivery manager | J82: Team plan + CI, 30-day pilot
A83: 82 | B83: Xebia France | C83: Java/Spring consultancies – France | D83: Paris, France | E83: Consultancy | F83: 56 | G83: =IF(F83>='Read me'!$B$12,"A",IF(F83>='Read me'!$B$13,"B","C")) -> C | H83: Java/Spring-heavy consultancy: can resell or embed RevIA in delivery (code audits, quality gates) and self-host it for clients who refuse SaaS code tools. | I83: Practice lead Java / Craft & quality lead | J83: Reseller / white-label + self-hosted licence
A84: 83 | B84: ekino | C84: Java/Spring consultancies – France | D84: Paris, France | E84: Digital agency (Havas) | F84: 56 | G84: =IF(F84>='Read me'!$B$12,"A",IF(F84>='Read me'!$B$13,"B","C")) -> C | H84: Java/Spring-heavy consultancy: can resell or embed RevIA in delivery (code audits, quality gates) and self-host it for clients who refuse SaaS code tools. | I84: Practice lead Java / Craft & quality lead | J84: Reseller / white-label + self-hosted licence
A85: 84 | B85: Smart Capital (Startup Tunisia) | C85: Channel partners | D85: Tunis, Tunisia | E85: Public startup programme | F85: 55 | G85: =IF(F85>='Read me'!$B$12,"A",IF(F85>='Read me'!$B$13,"B","C")) -> C | H85: Not an end buyer: a distribution partner that can put RevIA in front of many startups / dev teams at once. | I85: Program manager / partnerships | J85: Partner discount for portfolio companies | K85: Startup Act ecosystem; label + visibility.
A86: 85 | B86: Talan Tunisie (Talan Shore) | C86: Software firms – Tunisia | D86: Tunis, Tunisia | E86: Large nearshore centre | F86: 54 | G86: =IF(F86>='Read me'!$B$12,"A",IF(F86>='Read me'!$B$13,"B","C")) -> C | H86: Nearshore teams delivering Java/JS for EU clients need proof of code quality and security; RevIA adds a CI quality gate + SARIF reports, in French, cheaper than CodeRabbit/Copilot seats, self-hostable for client NDAs. | I86: CTO / Delivery or Quality manager | J86: Team plan + CI, 30-day pilot on one project | K86: Source: talan.com/en/practices/shore
A87: 86 | B87: S2M | C87: Software firms – Morocco | D87: Casablanca, Morocco | E87: Mid/large payments software | F87: 54 | G87: =IF(F87>='Read me'!$B$12,"A",IF(F87>='Read me'!$B$13,"B","C")) -> C | H87: Offshore/nearshore delivery for French-speaking clients; same quality-gate and SARIF evidence need; French UI and self-hosting help with client confidentiality clauses. | I87: CTO / Delivery manager | J87: Team plan + CI, 30-day pilot
A88: 87 | B88: Néosoft | C88: Java/Spring consultancies – France | D88: Rennes, France | E88: Large consultancy | F88: 54 | G88: =IF(F88>='Read me'!$B$12,"A",IF(F88>='Read me'!$B$13,"B","C")) -> C | H88: Java/Spring-heavy consultancy: can resell or embed RevIA in delivery (code audits, quality gates) and self-host it for clients who refuse SaaS code tools. | I88: Practice lead Java / Craft & quality lead | J88: Reseller / white-label + self-hosted licence | K88: Has offshore delivery in Tunisia.
A89: 88 | B89: Viseo | C89: Java/Spring consultancies – France | D89: Lyon / Paris, France | E89: Consultancy | F89: 54 | G89: =IF(F89>='Read me'!$B$12,"A",IF(F89>='Read me'!$B$13,"B","C")) -> C | H89: Java/Spring-heavy consultancy: can resell or embed RevIA in delivery (code audits, quality gates) and self-host it for clients who refuse SaaS code tools. | I89: Practice lead Java / Craft & quality lead | J89: Reseller / white-label + self-hosted licence
A90: 89 | B90: Onepoint | C90: Java/Spring consultancies – France | D90: Paris, France | E90: Consultancy | F90: 54 | G90: =IF(F90>='Read me'!$B$12,"A",IF(F90>='Read me'!$B$13,"B","C")) -> C | H90: Java/Spring-heavy consultancy: can resell or embed RevIA in delivery (code audits, quality gates) and self-host it for clients who refuse SaaS code tools. | I90: Practice lead Java / Craft & quality lead | J90: Reseller / white-label + self-hosted licence
A91: 90 | B91: Positive Thinking Company | C91: Java/Spring consultancies – France | D91: Paris, France | E91: Consultancy | F91: 54 | G91: =IF(F91>='Read me'!$B$12,"A",IF(F91>='Read me'!$B$13,"B","C")) -> C | H91: Java/Spring-heavy consultancy: can resell or embed RevIA in delivery (code audits, quality gates) and self-host it for clients who refuse SaaS code tools. | I91: Practice lead Java / Craft & quality lead | J91: Reseller / white-label + self-hosted licence
A92: 91 | B92: Telnet Holding | C92: Software firms – Tunisia | D92: Tunis, Tunisia | E92: Large engineering group | F92: 52 | G92: =IF(F92>='Read me'!$B$12,"A",IF(F92>='Read me'!$B$13,"B","C")) -> C | H92: Nearshore teams delivering Java/JS for EU clients need proof of code quality and security; RevIA adds a CI quality gate + SARIF reports, in French, cheaper than CodeRabbit/Copilot seats, self-hostable for client NDAs. | I92: CTO / Delivery or Quality manager | J92: Team plan + CI, 30-day pilot on one project | K92: Embedded/C focus: RevIA covers C.
A93: 92 | B93: HPS (Hightech Payment Systems) | C93: Software firms – Morocco | D93: Casablanca, Morocco | E93: Large, listed payments software | F93: 52 | G93: =IF(F93>='Read me'!$B$12,"A",IF(F93>='Read me'!$B$13,"B","C")) -> C | H93: Offshore/nearshore delivery for French-speaking clients; same quality-gate and SARIF evidence need; French UI and self-hosting help with client confidentiality clauses. | I93: CTO / Delivery manager | J93: Team plan + CI, 30-day pilot | K93: Payments → strict security, but long procurement.
A94: 93 | B94: Davidson Consulting | C94: Java/Spring consultancies – France | D94: Paris, France | E94: Large consultancy | F94: 52 | G94: =IF(F94>='Read me'!$B$12,"A",IF(F94>='Read me'!$B$13,"B","C")) -> C | H94: Java/Spring-heavy consultancy: can resell or embed RevIA in delivery (code audits, quality gates) and self-host it for clients who refuse SaaS code tools. | I94: Practice lead Java / Craft & quality lead | J94: Reseller / white-label + self-hosted licence
A95: 94 | B95: Infotel | C95: Java/Spring consultancies – France | D95: Paris, France | E95: Listed ESN | F95: 52 | G95: =IF(F95>='Read me'!$B$12,"A",IF(F95>='Read me'!$B$13,"B","C")) -> C | H95: Java/Spring-heavy consultancy: can resell or embed RevIA in delivery (code audits, quality gates) and self-host it for clients who refuse SaaS code tools. | I95: Practice lead Java / Craft & quality lead | J95: Reseller / white-label + self-hosted licence
A96: 95 | B96: SQLI | C96: Java/Spring consultancies – France | D96: Paris, France | E96: Listed digital agency | F96: 52 | G96: =IF(F96>='Read me'!$B$12,"A",IF(F96>='Read me'!$B$13,"B","C")) -> C | H96: Java/Spring-heavy consultancy: can resell or embed RevIA in delivery (code audits, quality gates) and self-host it for clients who refuse SaaS code tools. | I96: Practice lead Java / Craft & quality lead | J96: Reseller / white-label + self-hosted licence
A97: 96 | B97: Apside | C97: Java/Spring consultancies – France | D97: France | E97: Large ESN | F97: 52 | G97: =IF(F97>='Read me'!$B$12,"A",IF(F97>='Read me'!$B$13,"B","C")) -> C | H97: Java/Spring-heavy consultancy: can resell or embed RevIA in delivery (code audits, quality gates) and self-host it for clients who refuse SaaS code tools. | I97: Practice lead Java / Craft & quality lead | J97: Reseller / white-label + self-hosted licence
A98: 97 | B98: Sofrecom Tunisie (Orange group) | C98: Software firms – Tunisia | D98: Tunis, Tunisia | E98: Large | F98: 50 | G98: =IF(F98>='Read me'!$B$12,"A",IF(F98>='Read me'!$B$13,"B","C")) -> C | H98: Nearshore teams delivering Java/JS for EU clients need proof of code quality and security; RevIA adds a CI quality gate + SARIF reports, in French, cheaper than CodeRabbit/Copilot seats, self-hostable for client NDAs. | I98: CTO / Delivery or Quality manager | J98: Team plan + CI, 30-day pilot on one project | K98: Group tooling decisions often central (Orange).
A99: 98 | B99: Linedata Tunis | C99: Software firms – Tunisia | D99: Tunis, Tunisia | E99: Dev centre of a listed group | F99: 50 | G99: =IF(F99>='Read me'!$B$12,"A",IF(F99>='Read me'!$B$13,"B","C")) -> C | H99: Nearshore teams delivering Java/JS for EU clients need proof of code quality and security; RevIA adds a CI quality gate + SARIF reports, in French, cheaper than CodeRabbit/Copilot seats, self-hostable for client NDAs. | I99: CTO / Delivery or Quality manager | J99: Team plan + CI, 30-day pilot on one project
A100: 99 | B100: Groupe SII Maroc | C100: Software firms – Morocco | D100: Casablanca, Morocco | E100: 1,000–9,999 (GoodFirms) | F100: 50 | G100: =IF(F100>='Read me'!$B$12,"A",IF(F100>='Read me'!$B$13,"B","C")) -> C | H100: Offshore/nearshore delivery for French-speaking clients; same quality-gate and SARIF evidence need; French UI and self-hosting help with client confidentiality clauses. | I100: CTO / Delivery manager | J100: Team plan + CI, 30-day pilot
...

Sheet Outreach templates
A1: Email FR – école / bootcamp | B1: Objet : Revue de code IA pour vos apprenants – pilote gratuit d'un mois Bonjour, Je suis Nafissa Bridah, élève ingénieure à ESPRIT. Avec mon équipe, nous avons créé RevIA : une IA qui relit le code des apprenants comme un développeur senior (failles OWASP, bugs, bonnes pratiques), explique chaque problème et propose la correction. Pour une école, cela veut dire : un retour immédiat sur chaque projet, moins de temps de correction pour les formateurs, et un suivi de progression par apprenant. RevIA peut être installé sur vos propres serveurs. Je vous propose un pilote gratuit d'un mois sur une promotion. Une démo de 2 minutes : [lien vidéo]. Auriez-vous 20 minutes la semaine prochaine ? Bien cordialement, Nafissa
A2: Email FR – ESN / éditeur | B2: Objet : Un quality gate IA sur vos pull requests, hébergé chez vous Bonjour, RevIA relit automatiquement chaque pull request (Java, JS, PHP, Python, C…), signale les failles OWASP et les secrets en dur, propose la correction et bloque le merge sous un score que vous fixez. Les rapports SARIF s'affichent dans GitHub/GitLab et servent de preuve qualité pour vos clients. Contrairement aux outils américains (24 à 60 $ par développeur et par mois), RevIA s'installe sur vos serveurs, avec le modèle d'IA de votre choix ou un modèle local : le code de vos clients ne sort pas. Pilote gratuit de 30 jours sur un projet ? Démo de 2 minutes : [lien vidéo]. Cordialement, Nafissa Bridah
A3: Email EN – software company | B3: Subject: AI quality gate on your pull requests, self-hosted Hi, RevIA reviews every pull request (Java, JS, PHP, Python, C…), flags OWASP vulnerabilities and hard-coded secrets, proposes the fix and fails the build below the score you set. SARIF reports show up in GitHub/GitLab code scanning. Unlike US tools priced at $24–60 per developer per month, RevIA can run on your own servers with the LLM of your choice, or a local model, so client code never leaves your network. Would a free 30-day pilot on one project be useful? 2-minute demo: [video link]. Best regards, Nafissa Bridah
A4: LinkedIn note (300 chars) | B4: Bonjour [Prénom], je développe RevIA, une revue de code IA (OWASP, corrections expliquées, quality gate CI) auto-hébergeable. Je cherche 5 équipes pour un pilote gratuit d'un mois. Ça vous parlerait ?
